myutils/__init__.py
myutils/core.py
myutilslitdddddd-0.1.1.dist-info/METADATA
myutilslitdddddd-0.1.1.dist-info/WHEEL
myutilslitdddddd-0.1.1.dist-info/top_level.txt
myutilslitdddddd-0.1.1.dist-info/RECORD
