Metadata-Version: 2.4
Name: myutilslitdddddd
Version: 0.1.1
Summary: 一个自定义工具函数bao 哈哈哈
Home-page: https://github.com/yourname/myutils
Author: Your Name
Author-email: your@email.com
Classifier: Programming Language :: Python :: 3
Classifier: License :: OSI Approved :: MIT License
Classifier: Operating System :: OS Independent
Requires-Python: >=3.11
Dynamic: author
Dynamic: author-email
Dynamic: classifier
Dynamic: home-page
Dynamic: requires-python
Dynamic: summary
